mockgcp/__init__.py
mockgcp/storage/__init__.py
mockgcp/storage/backend.py
mockgcp/storage/blob.py
mockgcp/storage/bucket.py
mockgcp/storage/client.py
mock_gcp-0.2.0.dist-info/METADATA
mock_gcp-0.2.0.dist-info/WHEEL
mock_gcp-0.2.0.dist-info/licenses/LICENSE
mock_gcp-0.2.0.dist-info/RECORD
