Metadata-Version: 2.4
Name: mock-gcp
Version: 0.2.0
Summary: A library that allows to mock out GCP services in unit tests.
Author-email: Alexandra Abbas <alexandra.abbas@datatonic.com>
License-File: LICENSE
Classifier: Development Status :: 3 - Alpha
Classifier: Intended Audience :: Developers
Classifier: License :: OSI Approved :: MIT License
Classifier: Programming Language :: Python :: 3.9
Classifier: Programming Language :: Python :: 3.10
Classifier: Programming Language :: Python :: 3.11
Classifier: Programming Language :: Python :: 3.12
Classifier: Programming Language :: Python :: 3.13
Requires-Python: <3.14,>=3.9
Requires-Dist: google-cloud-storage<3.0,>=2.4
